list_packarge/__init__.py
list_packarge/nester.py
nester_pkg_edemrobin-1.1.2.dist-info/LICENSE
nester_pkg_edemrobin-1.1.2.dist-info/METADATA
nester_pkg_edemrobin-1.1.2.dist-info/WHEEL
nester_pkg_edemrobin-1.1.2.dist-info/top_level.txt
nester_pkg_edemrobin-1.1.2.dist-info/RECORD
