Metadata-Version: 2.1
Name: nester-pkg-edemrobin
Version: 1.1.2
Summary: A small list function package
Home-page: https://edemrobin.com
Author: Edem Robin
Author-email: edemrobin@gmail.com
License: UNKNOWN
Project-URL: Bug Tracker, https://github.com/pypa/sampleproject/issues
Platform: UNKNOWN
Classifier: Programming Language :: Python :: 3
Classifier: License :: OSI Approved :: MIT License
Classifier: Operating System :: OS Independent
Requires-Python: >=3.6
License-File: LICENSE
